AG_Parser/__init__.py
AG_Parser/parserr.py
AGParser-0.4.0.dist-info/METADATA
AGParser-0.4.0.dist-info/WHEEL
AGParser-0.4.0.dist-info/top_level.txt
AGParser-0.4.0.dist-info/RECORD
